samshee/__init__.py
samshee/__main__.py
samshee/samplesheetv2.py
samshee/sectionedsheet.py
samshee/validation.py
samshee-0.2.12.dist-info/licenses/LICENSE
samshee-0.2.12.dist-info/METADATA
samshee-0.2.12.dist-info/WHEEL
samshee-0.2.12.dist-info/top_level.txt
samshee-0.2.12.dist-info/RECORD
