Metadata-Version: 2.4
Name: samshee
Version: 0.2.12
Summary: A schema-agnostic parser and writer for illumina sample sheets v2.
Author-email: Jakob Simeth <jakob.simeth@ukr.de>, Matthew Lueder <luederm@chop.edu>
License: MIT License
Project-URL: Homepage, https://github.com/lit-regensburg/samshee
Project-URL: Bug Tracker, https://github.com/lit-regensburg/samshee/issues
Classifier: Programming Language :: Python :: 3
Classifier: Operating System :: OS Independent
Classifier: License :: OSI Approved :: MIT License
Classifier: Topic :: Scientific/Engineering :: Bio-Informatics
Classifier: Intended Audience :: Developers
Classifier: Intended Audience :: Science/Research
Classifier: Development Status :: 2 - Pre-Alpha
Requires-Python: >=3.9
License-File: LICENSE
Requires-Dist: jsonschema>=4.19
Requires-Dist: requests>=2.31.0
Dynamic: license-file
